LICENSE
MANIFEST.in
README.md
setup.py
QTool.egg-info/PKG-INFO
QTool.egg-info/SOURCES.txt
QTool.egg-info/dependency_links.txt
QTool.egg-info/top_level.txt
qtool/__init__.py
qtool/__version__.py
qtool/core.py