Metadata-Version: 2.1
Name: QTool
Version: 0.0.2
Summary: My short description for my project.
Home-page: https://github.com/yanqishi1
Author: yanqishi1
Author-email: 100462357@qq.com
License: MIT
Platform: UNKNOWN
Classifier: License :: OSI Approved :: MIT License
Classifier: Programming Language :: Python
Classifier: Programming Language :: Python :: 3
Classifier: Programming Language :: Python :: 3.6
Classifier: Programming Language :: Python :: Implementation :: CPython
Classifier: Programming Language :: Python :: Implementation :: PyPy
Requires-Python: >=3.6.0
